aces/__init__.py
aces/main.py
aces/fense/__init__.py
aces/fense/data.py
aces/fense/download_utils.py
aces/fense/evaluator.py
aces/fense/model.py
aces_metric-0.0.5.dist-info/licenses/LICENSE
aces_metric-0.0.5.dist-info/METADATA
aces_metric-0.0.5.dist-info/WHEEL
aces_metric-0.0.5.dist-info/top_level.txt
aces_metric-0.0.5.dist-info/RECORD
