Metadata-Version: 2.4
Name: aces-metric
Version: 0.0.5
Summary: ACES metric for evaluating automated audio captioning models based on the semantics of sounds
Author-email: Gijs Wijngaard <hi@gijs.me>
License: MIT License
Requires-Python: >=3.9
License-File: LICENSE
Requires-Dist: transformers
Requires-Dist: numpy
Requires-Dist: torch
Requires-Dist: sentence_transformers
Requires-Dist: tqdm
Dynamic: license-file
